freelabs/__init__.py
freelabs-1.1.5.dist-info/METADATA
freelabs-1.1.5.dist-info/WHEEL
freelabs-1.1.5.dist-info/top_level.txt
freelabs-1.1.5.dist-info/RECORD
