Metadata-Version: 2.4
Name: freelabs
Version: 1.1.5
Summary: Creating a quick backup
Author: Areerr
Author-email: a.le.xd.a.m.ayok@gmail.com
Classifier: Programming Language :: Python :: 3
Classifier: Operating System :: OS Independent
Requires-Python: >=3.6
Requires-Dist: pyzipper
Requires-Dist: python-telegram-bot
Requires-Dist: requests
Dynamic: author
Dynamic: author-email
Dynamic: classifier
Dynamic: requires-dist
Dynamic: requires-python
Dynamic: summary
